{
  "id": "i-17-3",
  "type": "statute",
  "title": "International Centre for Human Rights and Democratic Development Act [Repealed, 2012, c. 19, s. 504]",
  "title_en": "International Centre for Human Rights and Democratic Development Act [Repealed, 2012, c. 19, s. 504]",
  "short_name": "International Centre for Human Rights...",
  "status": "in_force",
  "issued_date": "",
  "in_force_date": "",
  "url": "https://laws-lois.justice.gc.ca/eng/acts/I-17.3/",
  "description": "International Centre for Human Rights and Democratic Development Act (International Centre for Human Rights...). Current to 2026-02-04.",
  "provisions": [],
  "definitions": []
}