{
  "id": "m-3-2",
  "type": "statute",
  "title": "Meat Inspection Act [Repealed, 2012, c. 24, s. 77]",
  "title_en": "Meat Inspection Act [Repealed, 2012, c. 24, s. 77]",
  "short_name": "Meat Inspection Act [Repealed, 2012, ...",
  "status": "in_force",
  "issued_date": "",
  "in_force_date": "",
  "url": "https://laws-lois.justice.gc.ca/eng/acts/M-3.2/",
  "description": "Meat Inspection Act (Meat Inspection Act [Repealed, 2012, ...). Current to 2026-02-04.",
  "provisions": [],
  "definitions": []
}